osonbot/__init__.py
osonbot/bot.py
osonbot/botbuilder.py
osonbot/cli.py
osonbot/database.py
osonbot/utils.py
osonbot-1.2.0.dist-info/METADATA
osonbot-1.2.0.dist-info/WHEEL
osonbot-1.2.0.dist-info/entry_points.txt
osonbot-1.2.0.dist-info/top_level.txt
osonbot-1.2.0.dist-info/RECORD
