Metadata-Version: 2.4
Name: osonbot
Version: 1.2.0
Summary: A simple and lightweight Telegram bot framework
Home-page: https://github.com/sinofarmonov323/osonbot
Author: https://t.me/jackson_rodger
Classifier: Programming Language :: Python :: 3
Classifier: License :: OSI Approved :: MIT License
Classifier: Operating System :: OS Independent
Requires-Python: >=3.10
Requires-Dist: httpx
Provides-Extra: builder
Requires-Dist: jsonbot; extra == "builder"
Provides-Extra: cli
Requires-Dist: watchdog; extra == "cli"
Dynamic: author
Dynamic: classifier
Dynamic: description
Dynamic: description-content-type
Dynamic: home-page
Dynamic: provides-extra
Dynamic: requires-dist
Dynamic: requires-python
Dynamic: summary
